{
    "name": "example/parent-module",
    "d4Shortcode": "",
    "title": "Parent Module",
    "titles": "Parent Modules",
    "category": "module",
    "attributes": {
        "icon": {
            "type": "object",
            "default": {
                "desktop": {
                    "value": {
                        "unicode": "&#x4e;",
                        "type": "divi",
                        "weight": "400"
                    }
                }
            }
        }
    },
    "customCssFields": {
        "contentContainer": {
            "subName":        "contentContainer",
            "selectorSuffix": " .child-module__content-container"
        },
        "title": {
            "subName":        "title",
            "selectorSuffix": " .child-module__title"
        },
        "content": {
            "subName":        "content",
            "selectorSuffix": " .child-module__content"
        },
        "icon": {
            "subName":        "icon",
            "selectorSuffix": " .child-module__icon.et-pb-icon"
        }
    }
}
